KBDD/EGtest.py
KBDD/KGML_to_Matrix.py
KBDD/Network_score_with_cor.py
KBDD/__init__.py
KBDD/alpha_estimation.py
KBDD/connect_adj_set.py
KBDD/deviation_calculation.py
KBDD/generate_ensemble_network.py
KBDD/import_references.py
KBDD/left_adj.py
KBDD/net_gen.py
KBDD/pns_construction.py
KBDD/rightmost_adj.py
KBDD/show_graph_with_labels.py
KBDD/truncated_power_law.py
KBDD-0.2.9.dist-info/LICENSE.txt
KBDD-0.2.9.dist-info/METADATA
KBDD-0.2.9.dist-info/WHEEL
KBDD-0.2.9.dist-info/top_level.txt
KBDD-0.2.9.dist-info/RECORD
