Metadata-Version: 2.1
Name: KBDD
Version: 0.2.9
Summary: A package for KBDD: a knowledge-based and data-driven method for genetic network construction
Author: Chen-Po Liao
Author-email: liaochenpo@gmail.com
License: MIT
Classifier: License :: OSI Approved :: MIT License
Classifier: Programming Language :: Python :: 3
Requires-Python: >=3.6
License-File: LICENSE.txt
